clementine/__init__.py
clementine/__main__.py
clementine/env.py
clementine/importing.py
clementine/py.typed
clementine/screenshot.py
clementine/about/__init__.py
clementine/about/dependencies.py
clementine/cli/__init__.py
clementine/cli/commands/__init__.py
clementine/cli/commands/_info.py
clementine/cli/commands/_screenshot.py
clementine-2024.4.6.dist-info/LICENSE
clementine-2024.4.6.dist-info/METADATA
clementine-2024.4.6.dist-info/WHEEL
clementine-2024.4.6.dist-info/entry_points.txt
clementine-2024.4.6.dist-info/top_level.txt
clementine-2024.4.6.dist-info/RECORD
