Metadata-Version: 2.1
Name: clementine
Version: 2024.4.6
Summary: 🍊 A sweet little Python package
Author-email: Suzen Fylke <codesue@users.noreply.github.com>
Project-URL: Documentation, https://codesue.github.io/clementine
Project-URL: Source Code, https://github.com/codesue/clementine
Project-URL: Bug Tracker, https://github.com/codesue/clementine/issues
Classifier: Development Status :: 1 - Planning
Classifier: Intended Audience :: Developers
Classifier: License :: OSI Approved :: MIT License
Classifier: Natural Language :: English
Classifier: Programming Language :: Python :: 3
Classifier: Topic :: Software Development :: Libraries
Classifier: Topic :: Utilities
Requires-Python: >=3.9
License-File: LICENSE
Provides-Extra: all
Requires-Dist: click ; extra == 'all'
Requires-Dist: playwright ; extra == 'all'
Requires-Dist: pyperclip ; extra == 'all'
Provides-Extra: blossom
Requires-Dist: bokeh ; extra == 'blossom'
Requires-Dist: gradio ; extra == 'blossom'
Requires-Dist: playwright ; extra == 'blossom'
Provides-Extra: fruit
Requires-Dist: catppuccin-matplotlib ; extra == 'fruit'
Requires-Dist: keras >=3 ; extra == 'fruit'
Requires-Dist: numpy ; extra == 'fruit'
Requires-Dist: pandas ; extra == 'fruit'
Requires-Dist: scikit-learn ; extra == 'fruit'
Requires-Dist: torch >=2 ; extra == 'fruit'
Provides-Extra: leaves
Requires-Dist: mkdocs-click ; extra == 'leaves'
Requires-Dist: mkdocs-walt ; extra == 'leaves'
Requires-Dist: mkdocstrings[python] ; extra == 'leaves'
Provides-Extra: pulp
Requires-Dist: datasets ; extra == 'pulp'
Requires-Dist: spacy ; extra == 'pulp'
Requires-Dist: transformers ; extra == 'pulp'
Requires-Dist: wandb ; extra == 'pulp'
Provides-Extra: rind
Requires-Dist: build ; extra == 'rind'
Requires-Dist: tomlkit ; extra == 'rind'
Requires-Dist: twine ; extra == 'rind'
Provides-Extra: seeds
Requires-Dist: bandit[toml] ; extra == 'seeds'
Requires-Dist: black ; extra == 'seeds'
Requires-Dist: isort ; extra == 'seeds'
Requires-Dist: mypy ; extra == 'seeds'
Requires-Dist: pip-tools ; extra == 'seeds'
Requires-Dist: pre-commit ; extra == 'seeds'
Requires-Dist: pytest ; extra == 'seeds'
Requires-Dist: ruff ; extra == 'seeds'
Provides-Extra: sprout
Requires-Dist: notebook ; extra == 'sprout'
Requires-Dist: rich ; extra == 'sprout'
Provides-Extra: tree
Requires-Dist: bokeh ; extra == 'tree'
Requires-Dist: gradio ; extra == 'tree'
Requires-Dist: playwright ; extra == 'tree'
Requires-Dist: catppuccin-matplotlib ; extra == 'tree'
Requires-Dist: keras >=3 ; extra == 'tree'
Requires-Dist: numpy ; extra == 'tree'
Requires-Dist: pandas ; extra == 'tree'
Requires-Dist: scikit-learn ; extra == 'tree'
Requires-Dist: torch >=2 ; extra == 'tree'
Requires-Dist: mkdocs-click ; extra == 'tree'
Requires-Dist: mkdocs-walt ; extra == 'tree'
Requires-Dist: mkdocstrings[python] ; extra == 'tree'
Requires-Dist: datasets ; extra == 'tree'
Requires-Dist: spacy ; extra == 'tree'
Requires-Dist: transformers ; extra == 'tree'
Requires-Dist: wandb ; extra == 'tree'
Requires-Dist: build ; extra == 'tree'
Requires-Dist: tomlkit ; extra == 'tree'
Requires-Dist: twine ; extra == 'tree'
Requires-Dist: bandit[toml] ; extra == 'tree'
Requires-Dist: black ; extra == 'tree'
Requires-Dist: isort ; extra == 'tree'
Requires-Dist: mypy ; extra == 'tree'
Requires-Dist: pip-tools ; extra == 'tree'
Requires-Dist: pre-commit ; extra == 'tree'
Requires-Dist: pytest ; extra == 'tree'
Requires-Dist: ruff ; extra == 'tree'
Requires-Dist: notebook ; extra == 'tree'
Requires-Dist: rich ; extra == 'tree'
